k2dg/__init__.py
k2dg/_cli.py
k2dg/_parse.py
k2dg/_print.py
k2dg/conversion.py
k2dg-0.1.2.dist-info/LICENSE
k2dg-0.1.2.dist-info/METADATA
k2dg-0.1.2.dist-info/WHEEL
k2dg-0.1.2.dist-info/entry_points.txt
k2dg-0.1.2.dist-info/top_level.txt
k2dg-0.1.2.dist-info/RECORD
